[
  {
    "_id": "596776c9fbeb61956865d9c0",
    "index": 0,
    "guid": "4d6fce60-7e3d-4d26-b13a-c62fee673e92",
    "isActive": false,
    "balance": "$2,541.98",
    "picture": "http://placehold.it/32x32",
    "age": 25,
    "eyeColor": "blue",
    "name": {
      "first": "Margaret",
      "last": "Fowler"
    },
    "company": "EXERTA",
    "email": "margaret.fowler@exerta.io",
    "phone": "+1 (974) 479-3856",
    "address": "951 Bergen Street, Roderfield, Montana, 3255",
    "about": "Aliqua magna nostrud exercitation amet laboris anim exercitation non anim eiusmod cupidatat quis labore. In ut reprehenderit fugiat nisi laboris cupidatat. Mollit tempor aute consectetur labore eu ut. Amet ex aliquip nulla reprehenderit officia occaecat incididunt proident reprehenderit ut sint. Duis commodo adipisicing laborum id cillum ullamco ad pariatur consequat adipisicing. Qui deserunt labore cillum nulla.",
    "registered": "Wednesday, October 26, 2016 6:01 AM",
    "latitude": "-23.959026",
    "longitude": "-85.228795",
    "tags": [
      "est",
      "minim",
      "quis",
      "qui",
      "cillum"
    ],
    "range": [
      0,
      1,
      2,
      3,
      4,
      5,
      6,
      7,
      8,
      9
    ],
    "friends": [
      {
        "id": 0,
        "name": "Wiley Tyson"
      },
      {
        "id": 1,
        "name": "Vega Savage"
      },
      {
        "id": 2,
        "name": "Jordan Harrison"
      }
    ],
    "greeting": "Hello, Margaret! You have 5 unread messages.",
    "favoriteFruit": "banana"
  },
  {
    "_id": "596776cac1b7418c1c102146",
    "index": 1,
    "guid": "799d1a0f-8568-489d-88d9-608f081b7b9c",
    "isActive": true,
    "balance": "$1,085.84",
    "picture": "http://placehold.it/32x32",
    "age": 21,
    "eyeColor": "blue",
    "name": {
      "first": "Young",
      "last": "Crawford"
    },
    "company": "PAPRIKUT",
    "email": "young.crawford@paprikut.biz",
    "phone": "+1 (948) 505-2684",
    "address": "352 Hendrickson Place, Glendale, Delaware, 5739",
    "about": "Nisi aute elit eiusmod nisi pariatur consequat. Ipsum proident irure ut id enim eiusmod. Fugiat consequat do culpa in qui dolor incididunt sint velit ex Lorem. Consequat elit laborum excepteur eu sint non. Adipisicing et officia amet magna tempor aliquip enim proident. Aute ut excepteur labore ex eiusmod cupidatat occaecat irure reprehenderit velit veniam magna sit laboris. Est non veniam sit laborum culpa magna enim voluptate magna est ea laboris ipsum.",
    "registered": "Wednesday, December 24, 2014 3:47 AM",
    "latitude": "54.695672",
    "longitude": "-152.848082",
    "tags": [
      "consequat",
      "velit",
      "eiusmod",
      "aute",
      "laboris"
    ],
    "range": [
      0,
      1,
      2,
      3,
      4,
      5,
      6,
      7,
      8,
      9
    ],
    "friends": [
      {
        "id": 0,
        "name": "Viola Chavez"
      },
      {
        "id": 1,
        "name": "Lina Sims"
      },
      {
        "id": 2,
        "name": "Hammond Acevedo"
      }
    ],
    "greeting": "Hello, Young! You have 9 unread messages.",
    "favoriteFruit": "apple"
  },
  {
    "_id": "596776cad6613c2947fa6f64",
    "index": 2,
    "guid": "4cc3a314-d943-4e89-afbe-bb05ce75ca47",
    "isActive": true,
    "balance": "$2,402.84",
    "picture": "http://placehold.it/32x32",
    "age": 34,
    "eyeColor": "blue",
    "name": {
      "first": "Annie",
      "last": "Dean"
    },
    "company": "AQUACINE",
    "email": "annie.dean@aquacine.tv",
    "phone": "+1 (848) 450-3376",
    "address": "946 Quay Street, Oretta, Oregon, 8287",
    "about": "Excepteur ut nisi elit cupidatat. Ut aliquip cillum sint aliqua duis pariatur quis cupidatat ea fugiat pariatur. Nulla commodo est adipisicing pariatur excepteur sit commodo enim velit irure veniam tempor id reprehenderit.",
    "registered": "Monday, January 2, 2017 1:54 PM",
    "latitude": "45.720761",
    "longitude": "-165.902302",
    "tags": [
      "mollit",
      "sit",
      "veniam",
      "eu",
      "exercitation"
    ],
    "range": [
      0,
      1,
      2,
      3,
      4,
      5,
      6,
      7,
      8,
      9
    ],
    "friends": [
      {
        "id": 0,
        "name": "Graves Mccullough"
      },
      {
        "id": 1,
        "name": "Tillman Flowers"
      },
      {
        "id": 2,
        "name": "Dorothy Ramos"
      }
    ],
    "greeting": "Hello, Annie! You have 6 unread messages.",
    "favoriteFruit": "strawberry"
  },
  {
    "_id": "596776ca87e4fcb9b329d352",
    "index": 3,
    "guid": "2f6f26b3-9d87-4a08-a058-ca409147bbbb",
    "isActive": true,
    "balance": "$2,621.51",
    "picture": "http://placehold.it/32x32",
    "age": 36,
    "eyeColor": "blue",
    "name": {
      "first": "Evangelina",
      "last": "Allen"
    },
    "company": "ELENTRIX",
    "email": "evangelina.allen@elentrix.org",
    "phone": "+1 (936) 564-2919",
    "address": "695 Newport Street, Cannondale, Kentucky, 5117",
    "about": "Voluptate sint veniam irure nisi adipisicing laborum quis enim occaecat deserunt ad qui ad eu. Ut commodo enim duis dolor consectetur. Ipsum aute commodo velit sunt laborum nulla officia veniam occaecat laborum et consequat dolor nisi. Sit sit duis pariatur eiusmod deserunt aute velit do ut duis mollit voluptate eiusmod. Occaecat dolor consequat Lorem aliqua. Amet minim incididunt ea proident eiusmod amet.",
    "registered": "Saturday, May 31, 2014 4:43 PM",
    "latitude": "-44.733003",
    "longitude": "-61.738531",
    "tags": [
      "laboris",
      "est",
      "ut",
      "laborum",
      "consequat"
    ],
    "range": [
      0,
      1,
      2,
      3,
      4,
      5,
      6,
      7,
      8,
      9
    ],
    "friends": [
      {
        "id": 0,
        "name": "Rhodes Vance"
      },
      {
        "id": 1,
        "name": "Jan Mcguire"
      },
      {
        "id": 2,
        "name": "Hodge Bush"
      }
    ],
    "greeting": "Hello, Evangelina! You have 8 unread messages.",
    "favoriteFruit": "banana"
  },
  {
    "_id": "596776cafd3c2b915a6fe506",
    "index": 4,
    "guid": "b2b6b64f-cf1b-4514-b13a-ce2f635d5c4e",
    "isActive": false,
    "balance": "$3,882.53",
    "picture": "http://placehold.it/32x32",
    "age": 28,
    "eyeColor": "brown",
    "name": {
      "first": "Laurie",
      "last": "Buchanan"
    },
    "company": "INSECTUS",
    "email": "laurie.buchanan@insectus.com",
    "phone": "+1 (954) 491-2386",
    "address": "722 Vanderbilt Avenue, Fowlerville, Arizona, 5006",
    "about": "Magna reprehenderit in ea sint et incididunt ut voluptate. Ut qui id laboris nostrud velit sit irure qui. Sit ad in fugiat aliquip. Pariatur amet commodo mollit dolor do reprehenderit cupidatat proident et esse minim cupidatat. Cillum sunt et mollit et non anim sint exercitation adipisicing reprehenderit incididunt minim ex.",
    "registered": "Saturday, May 7, 2016 1:41 PM",
    "latitude": "7.683983",
    "longitude": "20.063536",
    "tags": [
      "tempor",
      "in",
      "deserunt",
      "ullamco",
      "minim"
    ],
    "range": [
      0,
      1,
      2,
      3,
      4,
      5,
      6,
      7,
      8,
      9
    ],
    "friends": [
      {
        "id": 0,
        "name": "Whitley Willis"
      },
      {
        "id": 1,
        "name": "Whitney Davidson"
      },
      {
        "id": 2,
        "name": "Carole Clarke"
      }
    ],
    "greeting": "Hello, Laurie! You have 5 unread messages.",
    "favoriteFruit": "apple"
  },
  {
    "_id": "596776ca1747f5b989f7e8c7",
    "index": 5,
    "guid": "511ad84c-fac9-4a9b-9bfd-ffb89ec1a7fd",
    "isActive": true,
    "balance": "$3,208.89",
    "picture": "http://placehold.it/32x32",
    "age": 24,
    "eyeColor": "green",
    "name": {
      "first": "Letitia",
      "last": "Albert"
    },
    "company": "FORTEAN",
    "email": "letitia.albert@fortean.me",
    "phone": "+1 (804) 533-3056",
    "address": "290 Quentin Road, Remington, Federated States Of Micronesia, 6971",
    "about": "Id culpa ut aliqua incididunt officia sint nulla consequat sit ad. Sit ipsum quis mollit magna consectetur. In duis laboris labore eiusmod officia id irure velit labore laboris.",
    "registered": "Saturday, March 8, 2014 9:54 PM",
    "latitude": "-60.351377",
    "longitude": "50.088663",
    "tags": [
      "sint",
      "sint",
      "veniam",
      "qui",
      "nisi"
    ],
    "range": [
      0,
      1,
      2,
      3,
      4,
      5,
      6,
      7,
      8,
      9
    ],
    "friends": [
      {
        "id": 0,
        "name": "Milagros Pena"
      },
      {
        "id": 1,
        "name": "Julianne Flores"
      },
      {
        "id": 2,
        "name": "Bartlett Mckinney"
      }
    ],
    "greeting": "Hello, Letitia! You have 7 unread messages.",
    "favoriteFruit": "banana"
  },
  {
    "_id": "596776ca48d992c5c9a298ae",
    "index": 6,
    "guid": "f45f0517-c9d3-454c-b26a-2599cf0679af",
    "isActive": true,
    "balance": "$1,390.30",
    "picture": "http://placehold.it/32x32",
    "age": 29,
    "eyeColor": "green",
    "name": {
      "first": "Salas",
      "last": "Wilcox"
    },
    "company": "KINETICA",
    "email": "salas.wilcox@kinetica.name",
    "phone": "+1 (926) 420-3740",
    "address": "635 Thatford Avenue, Williston, American Samoa, 5036",
    "about": "Adipisicing sint dolor velit elit esse veniam. Irure excepteur nulla incididunt aliqua fugiat culpa adipisicing culpa. Ipsum sunt aute sit occaecat excepteur laborum sint.",
    "registered": "Thursday, February 25, 2016 7:10 AM",
    "latitude": "57.994651",
    "longitude": "-167.242027",
    "tags": [
      "minim",
      "tempor",
      "in",
      "ullamco",
      "pariatur"
    ],
    "range": [
      0,
      1,
      2,
      3,
      4,
      5,
      6,
      7,
      8,
      9
    ],
    "friends": [
      {
        "id": 0,
        "name": "Moses Houston"
      },
      {
        "id": 1,
        "name": "Bush Barber"
      },
      {
        "id": 2,
        "name": "Sloan Paul"
      }
    ],
    "greeting": "Hello, Salas! You have 5 unread messages.",
    "favoriteFruit": "apple"
  },
  {
    "_id": "596776cad337d77e6eb548fd",
    "index": 7,
    "guid": "7b8fc284-6a32-4bd6-8613-aae22faa8006",
    "isActive": false,
    "balance": "$1,412.83",
    "picture": "http://placehold.it/32x32",
    "age": 30,
    "eyeColor": "brown",
    "name": {
      "first": "Leona",
      "last": "Murphy"
    },
    "company": "OATFARM",
    "email": "leona.murphy@oatfarm.ca",
    "phone": "+1 (891) 482-2393",
    "address": "195 Miami Court, Dana, Iowa, 3484",
    "about": "Eu elit eu magna Lorem et duis proident pariatur. Lorem occaecat velit occaecat deserunt ad nulla. Irure laborum officia pariatur enim elit fugiat laboris do reprehenderit. Velit voluptate ipsum eiusmod dolor in non.",
    "registered": "Tuesday, May 6, 2014 10:25 AM",
    "latitude": "-14.548478",
    "longitude": "34.983165",
    "tags": [
      "consequat",
      "nisi",
      "nulla",
      "non",
      "sint"
    ],
    "range": [
      0,
      1,
      2,
      3,
      4,
      5,
      6,
      7,
      8,
      9
    ],
    "friends": [
      {
        "id": 0,
        "name": "Maddox Morgan"
      },
      {
        "id": 1,
        "name": "Rosemarie Davenport"
      },
      {
        "id": 2,
        "name": "Summers Good"
      }
    ],
    "greeting": "Hello, Leona! You have 5 unread messages.",
    "favoriteFruit": "banana"
  },
  {
    "_id": "596776ca8e022158fe10197a",
    "index": 8,
    "guid": "9bc25c9b-073b-46e0-b6aa-88074032301f",
    "isActive": false,
    "balance": "$1,906.84",
    "picture": "http://placehold.it/32x32",
    "age": 31,
    "eyeColor": "blue",
    "name": {
      "first": "Cochran",
      "last": "Romero"
    },
    "company": "COMTRAIL",
    "email": "cochran.romero@comtrail.co.uk",
    "phone": "+1 (918) 476-3762",
    "address": "689 Ovington Avenue, Lindisfarne, New York, 292",
    "about": "Magna voluptate aliqua laborum esse dolore Lorem et nostrud ut consectetur id consequat duis cillum. Ullamco voluptate ad culpa veniam commodo consequat. Ad Lorem mollit consectetur elit incididunt aliqua aute ex officia velit. Deserunt elit nulla duis cillum et. Proident sit consequat ex est amet mollit eu amet labore labore minim sit.",
    "registered": "Thursday, July 2, 2015 7:18 PM",
    "latitude": "-14.239402",
    "longitude": "150.038218",
    "tags": [
      "commodo",
      "mollit",
      "commodo",
      "consectetur",
      "irure"
    ],
    "range": [
      0,
      1,
      2,
      3,
      4,
      5,
      6,
      7,
      8,
      9
    ],
    "friends": [
      {
        "id": 0,
        "name": "Castillo Stone"
      },
      {
        "id": 1,
        "name": "Petty Hooper"
      },
      {
        "id": 2,
        "name": "Carson Hudson"
      }
    ],
    "greeting": "Hello, Cochran! You have 10 unread messages.",
    "favoriteFruit": "strawberry"
  },
  {
    "_id": "596776ca662e758beff7b9f0",
    "index": 9,
    "guid": "07d5a612-0818-402a-a7b1-c2be388278ca",
    "isActive": true,
    "balance": "$3,916.85",
    "picture": "http://placehold.it/32x32",
    "age": 32,
    "eyeColor": "blue",
    "name": {
      "first": "Gordon",
      "last": "Gallegos"
    },
    "company": "EBIDCO",
    "email": "gordon.gallegos@ebidco.net",
    "phone": "+1 (982) 433-2606",
    "address": "331 Brown Street, Stagecoach, Minnesota, 4834",
    "about": "Do consequat minim duis pariatur ut non nostrud cillum amet esse ut est dolore. Nulla laborum deserunt nisi cillum eu adipisicing duis adipisicing id. Commodo consequat officia consequat aliquip ut ad voluptate pariatur esse.",
    "registered": "Monday, July 18, 2016 10:28 PM",
    "latitude": "-83.458185",
    "longitude": "-150.961406",
    "tags": [
      "sit",
      "minim",
      "irure",
      "irure",
      "dolor"
    ],
    "range": [
      0,
      1,
      2,
      3,
      4,
      5,
      6,
      7,
      8,
      9
    ],
    "friends": [
      {
        "id": 0,
        "name": "Torres Mcdowell"
      },
      {
        "id": 1,
        "name": "Allie Salinas"
      },
      {
        "id": 2,
        "name": "Zamora Bradford"
      }
    ],
    "greeting": "Hello, Gordon! You have 9 unread messages.",
    "favoriteFruit": "strawberry"
  }
]
